prediction_market_agent_tooling/abis/agentresultmapping.abi.json
prediction_market_agent_tooling/abis/debuggingcontract.abi.json
prediction_market_agent_tooling/abis/depositablewrapper_erc20.abi.json
prediction_market_agent_tooling/abis/erc1155.abi.json
prediction_market_agent_tooling/abis/erc20.abi.json
prediction_market_agent_tooling/abis/erc4626.abi.json
prediction_market_agent_tooling/abis/erc721.abi.json
prediction_market_agent_tooling/abis/gvp2_settlement.abi.json
prediction_market_agent_tooling/abis/omen_dxdao.abi.json
prediction_market_agent_tooling/abis/omen_fpmm.abi.json
prediction_market_agent_tooling/abis/omen_fpmm_conditionaltokens.abi.json
prediction_market_agent_tooling/abis/omen_fpmm_factory.abi.json
prediction_market_agent_tooling/abis/omen_kleros.abi.json
prediction_market_agent_tooling/abis/omen_oracle.abi.json
prediction_market_agent_tooling/abis/omen_realitio.abi.json
prediction_market_agent_tooling/abis/omen_thumbnailmapping.abi.json
prediction_market_agent_tooling/abis/ownable.abi.json
prediction_market_agent_tooling/abis/ownable_erc721.abi.json
prediction_market_agent_tooling/abis/processor.abi.json
prediction_market_agent_tooling/abis/proxy.abi.json
prediction_market_agent_tooling/abis/seer_gnosis_router.abi.json
prediction_market_agent_tooling/abis/seer_market_factory.abi.json
prediction_market_agent_tooling/abis/swapr_quoter.abi.json
prediction_market_agent_tooling/abis/swapr_router.abi.json
prediction_market_agent_tooling/benchmark/__init__.py
prediction_market_agent_tooling/benchmark/agents.py
prediction_market_agent_tooling/benchmark/benchmark.py
prediction_market_agent_tooling/benchmark/utils.py
prediction_market_agent_tooling/chains.py
prediction_market_agent_tooling/config.py
prediction_market_agent_tooling/data_download/langfuse_data_downloader.py
prediction_market_agent_tooling/deploy/agent.py
prediction_market_agent_tooling/deploy/agent_example.py
prediction_market_agent_tooling/deploy/betting_strategy.py
prediction_market_agent_tooling-0.69.23.dist-info/METADATA
prediction_market_agent_tooling-0.69.23.dist-info/WHEEL
prediction_market_agent_tooling-0.69.23.dist-info/entry_points.txt
prediction_market_agent_tooling-0.69.23.dist-info/licenses/LICENSE
prediction_market_agent_tooling-0.69.23.dist-info/RECORD
