Metadata-Version: 2.4
Name: prediction-market-agent-tooling
Version: 0.69.23
Summary: Tools to benchmark, deploy and monitor prediction market agents.
License-File: LICENSE
Author: Gnosis
Requires-Python: >=3.10,<3.13
Classifier: Programming Language :: Python :: 3
Classifier: Programming Language :: Python :: 3.10
Classifier: Programming Language :: Python :: 3.11
Classifier: Programming Language :: Python :: 3.12
Provides-Extra: google
Provides-Extra: langchain
Provides-Extra: openai
Provides-Extra: optuna
Requires-Dist: autoflake (>=2.2.1,<3.0.0)
Requires-Dist: base58 (>=1.0.2,<2.0)
Requires-Dist: cowdao-cowpy (==1.0.1)
Requires-Dist: cron-validator (>=1.0.8,<2.0.0)
Requires-Dist: eth-account (>=0.13.0,<0.14.0)
Requires-Dist: eth-keys (>=0.6.1,<0.7.0)
Requires-Dist: eth-typing (>=5.0.0,<6.0.0)
Requires-Dist: functions-framework (>=3.5.0,<4.0.0)
Requires-Dist: google-api-python-client (==2.95.0) ; extra == "google"
Requires-Dist: google-cloud-functions (>=1.16.0,<2.0.0)
Requires-Dist: google-cloud-resource-manager (>=1.12.0,<2.0.0)
Requires-Dist: google-cloud-secret-manager (>=2.18.2,<3.0.0)
Requires-Dist: hishel (>=0.0.31,<0.0.32)
Requires-Dist: httpx (>=0.25.2,<1.0.0)
Requires-Dist: isort (>=5.13.2,<6.0.0)
Requires-Dist: langchain (>=1.0.0,<2.0.0) ; extra == "langchain"
Requires-Dist: langchain-community (>=0.0.19)
Requires-Dist: langchain-openai (>=1.0.0,<2.0.0) ; extra == "langchain"
Requires-Dist: langfuse (>=3.0.0,<4.0.0)
Requires-Dist: loguru (>=0.7.2,<0.8.0)
Requires-Dist: loky (>=3.4.1,<4.0.0)
Requires-Dist: numpy (>=1.26.4,<2.0.0)
Requires-Dist: openai (>=1.0.0,<2.0.0) ; extra == "openai"
Requires-Dist: optuna (>=4.1.0,<5.0.0) ; extra == "optuna"
Requires-Dist: pinatapy-vourhey (>=0.2.0,<0.3.0)
Requires-Dist: prompt-toolkit (>=3.0.43,<4.0.0)
Requires-Dist: proto-plus (>=1.0.0,<2.0.0)
Requires-Dist: protobuf (>=5.0.0,<6.0.0)
Requires-Dist: psycopg2-binary (>=2.9.9,<3.0.0)
Requires-Dist: py-clob-client (>=0.24.0,<0.25.0)
Requires-Dist: pydantic (>=2.6.1,<3.0.0)
Requires-Dist: pydantic-ai (>=1.0.3,<2.0.0)
Requires-Dist: pydantic-settings (>=2.4.0,<3.0.0)
Requires-Dist: pymongo (>=4.8.0,<5.0.0)
Requires-Dist: pytest-postgresql (>=6.1.1,<7.0.0)
Requires-Dist: python-dateutil (>=2.9.0.post0,<3.0.0)
Requires-Dist: python-json-logger (>=3.3.0,<4.0.0)
Requires-Dist: safe-cli (>=1.5.0,<2.0.0)
Requires-Dist: safe-eth-py (>=7.8.0,<8.0.0)
Requires-Dist: scikit-learn (>=1.3.1,<2.0.0)
Requires-Dist: sqlmodel (>=0.0.22,<0.0.23)
Requires-Dist: streamlit (>=1.31.0,<2.0.0)
Requires-Dist: subgrounds-gnosis (>=1.9.2,<2.0.0)
Requires-Dist: tabulate (>=0.9.0,<0.10.0)
Requires-Dist: tavily-python (>=0.5.0,<0.6.0)
Requires-Dist: tqdm (>=4.66.2,<5.0.0)
Requires-Dist: typer (>=0.9.0,<1.0.0)
Requires-Dist: types-cachetools (>=5.5.0.20240820,<6.0.0.0)
Requires-Dist: types-python-dateutil (>=2.9.0.20240906,<3.0.0.0)
Requires-Dist: types-pytz (>=2024.1.0.20240203,<2025.0.0.0)
Requires-Dist: types-requests (>=2.31.0.0,<3.0.0.0)
Requires-Dist: web3 (>=6,<8)
